CHANGES.rst
Dockerfile
MANIFEST.in
Makefile
README.rst
buildout.cfg
ez_setup.py
jenkins.cfg
requirements.txt
setup.py
versions-base.cfg
versions-dev.cfg
src/imio/__init__.py
src/imio.pm.ws.egg-info/PKG-INFO
src/imio.pm.ws.egg-info/SOURCES.txt
src/imio.pm.ws.egg-info/dependency_links.txt
src/imio.pm.ws.egg-info/entry_points.txt
src/imio.pm.ws.egg-info/namespace_packages.txt
src/imio.pm.ws.egg-info/not-zip-safe
src/imio.pm.ws.egg-info/requires.txt
src/imio.pm.ws.egg-info/top_level.txt
src/imio/pm/__init__.py
src/imio/pm/ws/README.txt
src/imio/pm/ws/WS4PM_client.py
src/imio/pm/ws/WS4PM_server.py
src/imio/pm/ws/WS4PM_types.py
src/imio/pm/ws/__init__.py
src/imio/pm/ws/config.py
src/imio/pm/ws/configure.zcml
src/imio/pm/ws/dumpedWSDL.txt
src/imio/pm/ws/extender.py
src/imio/pm/ws/interfaces.py
src/imio/pm/ws/overrides.py
src/imio/pm/ws/setuphandlers.py
src/imio/pm/ws/testing.py
src/imio/pm/ws/testing.zcml
src/imio/pm/ws/locales/imio.history.pot
src/imio/pm/ws/locales/imio.pm.ws.pot
src/imio/pm/ws/locales/plone.pot
src/imio/pm/ws/locales/sync_pos.sh
src/imio/pm/ws/locales/en/LC_MESSAGES/imio.history.po
src/imio/pm/ws/locales/en/LC_MESSAGES/imio.pm.ws.po
src/imio/pm/ws/locales/en/LC_MESSAGES/plone.po
src/imio/pm/ws/locales/fr/LC_MESSAGES/imio.history.po
src/imio/pm/ws/locales/fr/LC_MESSAGES/imio.pm.ws.po
src/imio/pm/ws/locales/fr/LC_MESSAGES/plone.po
src/imio/pm/ws/profiles/default/browserlayer.xml
src/imio/pm/ws/profiles/default/catalog.xml
src/imio/pm/ws/profiles/default/imio_pm_ws_marker.txt
src/imio/pm/ws/profiles/default/import_steps.xml
src/imio/pm/ws/profiles/default/metadata.xml
src/imio/pm/ws/profiles/default/rolemap.xml
src/imio/pm/ws/profiles/uninstall/browserlayer.xml
src/imio/pm/ws/profiles/uninstall/catalog.xml
src/imio/pm/ws/soap/__init__.py
src/imio/pm/ws/soap/basetypes.py
src/imio/pm/ws/soap/soapview.py
src/imio/pm/ws/soap/ws4pmwsdl.pt
src/imio/pm/ws/tests/WS4PMTestCase.py
src/imio/pm/ws/tests/__init__.py
src/imio/pm/ws/tests/emptyTestFile.txt
src/imio/pm/ws/tests/file_crash_libmagic.doc
src/imio/pm/ws/tests/largeTestFile.doc
src/imio/pm/ws/tests/mediumTestFile.odt
src/imio/pm/ws/tests/octetStreamTestFile.bin
src/imio/pm/ws/tests/smallTestFile.pdf
src/imio/pm/ws/tests/test_checkislinked.py
src/imio/pm/ws/tests/test_connection.py
