Metadata-Version: 2.1
Name: imio.pm.ws
Version: 3.8
Summary: WebServices for PloneMeeting
Home-page: http://svn.communesplone.org/svn/communesplone/imio.pm.ws/
Author: Gauthier Bastien
Author-email: gauthier@imio.be
License: GPL
Platform: UNKNOWN
Classifier: Development Status :: 6 - Mature
Classifier: Framework :: Plone
Classifier: Framework :: Plone :: 4.3
Classifier: License :: OSI Approved :: GNU General Public License (GPL)
Classifier: Programming Language :: Python
Classifier: Programming Language :: Python :: 2.7
Provides-Extra: test
